hx_toolkit/VERSION
hx_toolkit/__init__.py
hx_toolkit/admin.py
hx_toolkit/apps.py
hx_toolkit/db_dao.py
hx_toolkit/file_dao.py
hx_toolkit/models.py
hx_toolkit/tests.py
hx_toolkit/urls.py
hx_toolkit/views.py
hx_toolkit/management/__init__.py
hx_toolkit/management/commands/__init__.py
hx_toolkit/management/commands/thrive.py
hx_toolkit/migrations/0001_initial.py
hx_toolkit/migrations/0002_auto_20171212_0058.py
hx_toolkit/migrations/0003_auto_20171215_0313.py
hx_toolkit/migrations/0004_article_image_credit.py
hx_toolkit/migrations/0005_article_image_alt_text.py
hx_toolkit/migrations/0006_auto_20171226_1746.py
hx_toolkit/migrations/__init__.py
hx_toolkit/static/hx_toolkit_output/images/Applying_Scholarships_More_than_Money_1000.jpg
hx_toolkit/static/hx_toolkit_output/images/Applying_Scholarships_More_than_Money_480.jpg
hx_toolkit/static/hx_toolkit_output/images/Applying_Scholarships_More_than_Money_650.jpg
hx_toolkit/static/hx_toolkit_output/images/Applying_Scholarships_More_than_Money_780.jpg
hx_toolkit/static/hx_toolkit_output/images/Becoming_Better_Listener_1000.jpg
hx_toolkit/static/hx_toolkit_output/images/Becoming_Better_Listener_480.jpg
hx_toolkit/static/hx_toolkit_output/images/Becoming_Better_Listener_650.jpg
hx_toolkit/static/hx_toolkit_output/images/Becoming_Better_Listener_780.jpg
hx_toolkit/static/hx_toolkit_output/images/Between_College_Career_1000.jpg
hx_toolkit/static/hx_toolkit_output/images/Between_College_Career_480.jpg
hx_toolkit/static/hx_toolkit_output/images/Between_College_Career_650.jpg
hx_toolkit/static/hx_toolkit_output/images/Between_College_Career_780.jpg
hx_toolkit/static/hx_toolkit_output/images/Boost_study_skills_1000.jpeg
hx_toolkit/static/hx_toolkit_output/images/Boost_study_skills_480.jpeg
hx_toolkit/static/hx_toolkit_output/images/Boost_study_skills_650.jpeg
hx_toolkit/static/hx_toolkit_output/images/Boost_study_skills_780.jpeg
hx_toolkit/static/hx_toolkit_output/images/Considering_Graduate_Professional_School_1000.jpg
uw_hx_toolkit-2.7.13.dist-info/METADATA
uw_hx_toolkit-2.7.13.dist-info/WHEEL
uw_hx_toolkit-2.7.13.dist-info/top_level.txt
uw_hx_toolkit-2.7.13.dist-info/RECORD
