Metadata-Version: 2.4
Name: UW_HX_Toolkit
Version: 2.7.13
Summary: An application for managing and serving HXT content
Home-page: https://github.com/uw-it-aca/hx_toolkit
Author: UW-IT SETS
Author-email: aca-it@uw.edu
License: Apache License, Version 2.0
Classifier: Intended Audience :: Developers
Classifier: License :: OSI Approved :: Apache Software License
Classifier: Operating System :: OS Independent
Classifier: Programming Language :: Python
Requires-Dist: Django<6,>=5.2
Requires-Dist: django-compressor
Requires-Dist: pillow
Dynamic: author
Dynamic: author-email
Dynamic: classifier
Dynamic: description
Dynamic: home-page
Dynamic: license
Dynamic: requires-dist
Dynamic: summary
